nezha/__main__.py
nezha/config_parser.py
nezha/connection.py
nezha/context.py
nezha/host.py
nezha_ssh-0.1.0.dist-info/LICENSE
nezha_ssh-0.1.0.dist-info/METADATA
nezha_ssh-0.1.0.dist-info/WHEEL
nezha_ssh-0.1.0.dist-info/top_level.txt
nezha_ssh-0.1.0.dist-info/RECORD
