Metadata-Version: 2.1
Name: nezha-ssh
Version: 0.1.0
Summary: Organizing ssh servers in one shell.
Home-page: https://github.com/zhuzilin/NeZha
Author: zhuzilin
Author-email: zhuzilinallen@gmail.com
License: MIT
Platform: UNKNOWN
